{
    "University of Toronto": "#1E3765",
    "University of British Columbia": "#002145",
    "Simon Fraser University": "#991B1B",
    "University of Waterloo": "#FED34C",
    "Western University": "#4c1d95",
    "Queen's University": "#002452",
    "University of Victoria": "#0073BC",
    "McGill University": "#ED1B2F",
    "University of Alberta": "#275D38",
    "McMaster University": "#D10000",
    "York University": "#004A8D",
    "Emily Carr University": "#7c2d12",
    "OCAD University": "#7c3aed",
    "Embry-Riddle Aeronautical University": "#0c4a6e"
}